<?xml version="1.0" encoding="UTF-8" ?>
<!DOCTYPE mapper PUBLIC "-//mybatis.org//DTD Mapper 3.0//EN" "http://mybatis.org/dtd/mybatis-3-mapper.dtd" >
<mapper namespace="cyf.es.search.dao.TMInfoMapper" >
  <resultMap id="BaseResultMap" type="cyf.es.search.domain.TMInfo" >
    <!--
      WARNING - @mbggenerated
      This element is automatically generated by MyBatis Generator, do not modify.
    -->
    <id column="t_tm_detail_3_id" property="id" jdbcType="INTEGER" />
    <result column="t_tm_detail_3_tm_reg_nbr" property="tmRegNbr" jdbcType="VARCHAR" />
    <result column="t_tm_detail_3_tm_cn" property="tmCn" jdbcType="VARCHAR" />
    <result column="t_tm_detail_3_tm_applicant" property="tmApplicant" jdbcType="VARCHAR" />
    <result column="t_tm_detail_3_tm_class" property="tmClass" jdbcType="INTEGER" />
    <result column="t_tm_detail_3_tmdetail" property="tmdetail" jdbcType="LONGVARCHAR" />
    <result column="t_tm_detail_3_tm_en" property="tmEn" jdbcType="VARCHAR" />
  </resultMap>
  <sql id="Base_Column_List" >
    <!--
      WARNING - @mbggenerated
      This element is automatically generated by MyBatis Generator, do not modify.
    -->
    t_tm_detail_3.id as t_tm_detail_3_id,
    t_tm_detail_3.tm_reg_nbr as t_tm_detail_3_tm_reg_nbr,
   t_tm_detail_3.tm_cn as t_tm_detail_3_tm_cn,
    t_tm_detail_3.tm_applicant as t_tm_detail_3_tm_applicant,
    t_tm_detail_3.tm_class as t_tm_detail_3_tm_class,
    t_tm_detail_3.tmdetail as t_tm_detail_3_tmdetail,
    t_tm_detail_3.tm_en as t_tm_detail_3_tm_en
  </sql>

  <select id="selectMaxId" resultType="java.lang.Integer">
    select max(id)
    from t_tm_detail_3 t_tm_detail_3
  </select>

  <select id="selectByIDRange" resultMap="BaseResultMap" parameterType="cyf.es.search.domain.TMInfo" >
    select
    <include refid="Base_Column_List" />
    from t_tm_detail_3 t_tm_detail_3
    where
    t_tm_detail_3.id>=#{id,jdbcType=INTEGER} and t_tm_detail_3.id &lt; (#{id,jdbcType=INTEGER}+#{pageCnt})
  </select>







</mapper>